setup.cfg
setup.py
tictacs/__init__.py
tictacs/parse.py
tictacs/wrappers.py
tictacs.egg-info/PKG-INFO
tictacs.egg-info/SOURCES.txt
tictacs.egg-info/dependency_links.txt
tictacs.egg-info/pbr.json
tictacs.egg-info/requires.txt
tictacs.egg-info/top_level.txt