Metadata-Version: 1.1
Name: tictacs
Version: 0.0.3
Summary: Machine learning pipeline creation from config files
Home-page: https://github.com/andreasgrv/tictacs
Author: Andreas Grivas
Author-email: andreasgrv@gmail.com
License: BSD
Download-URL: https://github.com/andreasgrv/tictacs/tarball/0.0.3
Keywords: machine learning,pipeline,config
Platform: UNKNOWN
